{
    "wallpaper": "https:.dev/download/IMG.jpg",
    "warningText": "兵哥视界，完全免费，切勿付费购买！",
    "sites": [
        {
            "key": "豆瓣",
            "name": "💥兵哥视界💥未经兵哥授权，停止使用",
            "type": 3,
            "api": "csp_Douban",
            "searchable": 0,
            "indexs": 1
        },
        {
            "key": "配置中心",
            "name": "配置🧧中心",
            "type": 3,
            "api": "csp_Config",
            "searchable": 0,
            "changeable": 0,
            "indexs": 0,
            "style": {
                "type": "rect",
                "ratio": 1.597
            }
        },
        {
            "key": "push_agent",
            "name": "手机🧧推送",
            "type": 3,
            "api": "csp_Push",
            "searchable": 0,
            "filterable": 0,
            "changeable": 0
        }
    ],
    "spider": "./jar/xiaosa.jar",
    "notice": "未经授权，禁止使用",
    "ads": [
        "mozai.4gtv.tv",
        "mimg.0c1q0l.cn",
        "www.googletagmanager.com",
        "www.google-analytics.com",
        "mc.usihnbcq.cn",
        "mg.g1mm3d.cn",
        "mscs.svaeuzh.cn",
        "cnzz.hhttm.top",
        "tp.vinuxhome.com",
        "cnzz.mmstat.com",
        "www.baihuillq.com",
        "s23.cnzz.com",
        "z3.cnzz.com",
        "c.cnzz.com",
        "stj.v1vo.top",
        "z12.cnzz.com",
        "img.mosflower.cn",
        "tips.gamevvip.com",
        "ehwe.yhdtns.com",
        "xdn.cqqc3.com",
        "www.jixunkyy.cn",
        "sp.chemacid.cn",
        "hm.baidu.com",
        "s9.cnzz.com",
        "z6.cnzz.com",
        "um.cavuc.com",
        "mav.mavuz.com",
        "wofwk.aoidf3.com",
        "z5.cnzz.com",
        "xc.hubeijieshikj.cn",
        "tj.tianwenhu.com",
        "xg.gars57.cn",
        "k.jinxiuzhilv.com",
        "cdn.bootcss.com",
        "ppl.xunzhuo123.com",
        "xomk.jiangjunmh.top",
        "img.xunzhuo123.com",
        "z1.cnzz.com",
        "s13.cnzz.com",
        "xg.huataisangao.cn",
        "z7.cnzz.com",
        "z2.cnzz.com",
        "s96.cnzz.com",
        "q11.cnzz.com",
        "thy.dacedsfa.cn",
        "xg.whsbpw.cn",
        "s19.cnzz.com",
        "z8.cnzz.com",
        "s4.cnzz.com",
        "f5w.as12df.top",
        "ae01.alicdn.com",
        "www.92424.cn",
        "k.wudejia.com",
        "vivovip.mmszxc.top",
        "qiu.xixiqiu.com",
        "cdnjs.hnfenxun.com",
        "cms.qdwght.com"
    ]
}